azure/mgmt/fabric/__init__.py
azure/mgmt/fabric/_client.py
azure/mgmt/fabric/_configuration.py
azure/mgmt/fabric/_model_base.py
azure/mgmt/fabric/_patch.py
azure/mgmt/fabric/_serialization.py
azure/mgmt/fabric/_version.py
azure/mgmt/fabric/py.typed
azure/mgmt/fabric/aio/__init__.py
azure/mgmt/fabric/aio/_client.py
azure/mgmt/fabric/aio/_configuration.py
azure/mgmt/fabric/aio/_patch.py
azure/mgmt/fabric/aio/operations/__init__.py
azure/mgmt/fabric/aio/operations/_operations.py
azure/mgmt/fabric/aio/operations/_patch.py
azure/mgmt/fabric/models/__init__.py
azure/mgmt/fabric/models/_enums.py
azure/mgmt/fabric/models/_models.py
azure/mgmt/fabric/models/_patch.py
azure/mgmt/fabric/operations/__init__.py
azure/mgmt/fabric/operations/_operations.py
azure/mgmt/fabric/operations/_patch.py
azure_mgmt_fabric-1.0.0.dist-info/LICENSE
azure_mgmt_fabric-1.0.0.dist-info/METADATA
azure_mgmt_fabric-1.0.0.dist-info/WHEEL
azure_mgmt_fabric-1.0.0.dist-info/top_level.txt
azure_mgmt_fabric-1.0.0.dist-info/RECORD
